{
  "dokumentstatus": {
    "dokument": {
      "hangar_id": "5253348",
      "dok_id": "HD01SfU8",
      "rm": "2025/26",
      "beteckning": "SfU8",
      "typ": "bet",
      "subtyp": "bet",
      "doktyp": "bet",
      "typrubrik": "Betänkande 2025/26:SfU8",
      "dokumentnamn": "Betänkande",
      "debattnamn": "Debatt om förslag",
      "tempbeteckning": "",
      "organ": "SfU",
      "mottagare": "",
      "nummer": "8",
      "slutnummer": "0",
      "datum": "2026-01-14 00:00:00",
      "systemdatum": "2026-04-24 14:41:29",
      "publicerad": "2025-09-25 15:30:18",
      "titel": "Riksrevisionens rapport om Migrationsverkets hantering av medborgarskapsärenden",
      "subtitel": "",
      "status": "Webbpublicering",
      "htmlformat": "html",
      "relaterat_id": "",
      "source": "RIM",
      "sourceid": "e2b70799-69c2-4653-af1f-5b9785fef757",
      "dokument_url_text": "https://data.riksdagen.se/dokument/HD01SfU8/text",
      "dokument_url_html": "https://data.riksdagen.se/dokument/HD01SfU8",
      "dokumentstatus_url_xml": "https://data.riksdagen.se/dokumentstatus/HD01SfU8",
      "utskottsforslag_url_xml": "https://data.riksdagen.se/utskottsforslag/HD01SfU8",
      "html": "<style><!--\r\n .w600px{width: 600px;font-family:Verdana, Geneva, sans-serif}\r\nh2.dtyp{font-size:1.5em !important;} \r\n@page Section1 { size:467.8pt 686.05pt; margin:45.35pt 102.05pt 73.7pt 70.85pt }\r\ndiv.Section1 { page:Section1 }\r\nzbody { text-align:justify; line-height:12.5pt; font-family:'Verdana'; font-size:9.5pt }\r\nzh1, h2, h3, h4, h5, h6, p { margin:3.1pt 0pt 0pt }\r\nzli, table { margin-top:3.1pt; margin-bottom:0pt }\r\nzh1 { margin-top:3.1pt; margin-bottom:12pt; text-align:left; page-break-inside:auto; page-break-after:avoid; line-height:12.5pt; font-family:'Verdana'; font-size:16pt; font-weight:normal; color:#000000 }\r\nzh2 { margin-top:20pt; margin-bottom:6pt; text-align:left; page-break-inside:avoid; page-break-after:avoid; line-height:12.5pt; font-family:'Verdana'; font-size:13.5pt; font-weight:normal; color:#000000 }\r\nzh3 { margin-top:20pt; margin-bottom:3.1pt; text-align:left; page-break-inside:avoid; page-break-after:avoid; line-height:12.5pt; font-family:'Verdana'; font-size:10.5pt; font-weight:bold; color:#000000 }\r\nzh4 { margin-top:15pt; margin-bottom:3.1pt; text-align:left; page-break-inside:avoid; page-break-after:avoid; line-height:12.5pt; font-family:'Verdana'; font-size:10.5pt; font-weight:normal; font-style:italic; color:#000000 }\r\nzh5 { margin-top:6.25pt; margin-bottom:0pt; text-align:left; page-break-inside:avoid; page-break-after:avoid; line-height:12.5pt; font-family:'Verdana'; font-size:9.5pt; font-weight:bold; color:#000000 }\r\nzh6 { margin-top:6.25pt; margin-bottom:0pt; text-align:left; page-break-inside:avoid; page-break-after:avoid; line-height:12.5pt; font-family:'Verdana'; font-size:9.5pt; font-weight:normal; font-style:italic; color:#000000 }\r\n.Heading7 { margin-top:2pt; margin-bottom:0pt; text-align:left; page-break-inside:avoid; page-break-after:avoid; line-height:12.5pt; font-family:'Verdana'; font-size:9.5pt; font-weight:normal; font-style:italic; color:#243f60; -aw-style-name:heading7 }\r\n.Heading8 { margin-top:2pt; margin-bottom:0pt; text-align:left; page-break-inside:avoid; page-break-after:avoid; line-height:12.5pt; font-family:'Verdana'; font-size:9pt; font-weight:normal; color:#272727; -aw-style-name:heading8 }\r\n.Heading9 { margin-top:2pt; margin-bottom:0pt; text-align:left; page-break-inside:avoid; page-break-after:avoid; line-height:12.5pt; font-family:'Verdana'; font-size:9pt; font-weight:normal; font-style:italic; color:#272727; -aw-style-name:heading9 }\r\n.Avsnittsrubrik { margin-top:0pt; margin-bottom:27.7pt; text-align:left; page-break-before:always; page-break-after:avoid; line-height:normal; font-family:'Verdana'; font-size:16pt }\r\n.Avvikandemeningrubrik { margin-top:0pt; margin-bottom:3.1pt; text-align:left; page-break-inside:avoid; page-break-after:avoid; line-height:12.5pt; font-family:'Verdana'; font-size:10.5pt; font-weight:bold }\r\n.BalloonText { margin-top:3.1pt; margin-bottom:0pt; text-align:justify; line-height:normal; font-family:Tahoma; font-size:8pt }\r\n.Bilaga { margin-top:0pt; margin-bottom:0pt; text-align:left; page-break-before:always; page-break-after:avoid; line-height:normal; widows:0; orphans:0; font-family:'Verdana'; font-size:8pt; font-variant:small-caps; text-decoration:underline }\r\n.Bilagerubrik { margin-top:0pt; margin-bottom:17.7pt; text-align:left; page-break-after:auto; line-height:normal; widows:0; orphans:0; font-family:'Verdana'; font-size:16pt }\r\n.Bild-R { margin-top:12pt; margin-bottom:3pt; text-align:left; page-break-inside:avoid; page-break-after:avoid; line-height:10pt; font-family:'Verdana'; font-size:9pt; font-weight:bold }\r\n.Bild-Rubrik { margin-top:12pt; margin-bottom:3pt; text-align:left; page-break-inside:avoid; page-break-after:avoid; line-height:10pt; font-family:'Verdana'; font-size:9pt; font-weight:bold }\r\n.Bild-Underrubrik { margin-top:0pt; margin-bottom:1pt; text-align:left; page-break-inside:avoid; page-break-after:avoid; line-height:8pt; font-family:'Verdana'; font-size:8pt; font-weight:normal; font-style:italic }\r\n.BodyText { margin-top:3.1pt; margin-bottom:0pt; text-align:left; line-height:12.5pt; font-family:'Verdana'; font-size:9.5pt }\r\n.BodyTextIndent2 { margin-top:3.1pt; margin-left:14.15pt; margin-bottom:6pt; text-align:justify; line-height:200%; font-family:'Verdana'; font-size:9.5pt }\r\n.Citatindrag { margin-top:0pt; margin-left:14.2pt; margin-bottom:6.1pt; text-indent:14.2pt; text-align:justify; line-height:10pt; font-family:'Verdana'; font-size:9.5pt }\r\n.CommentText { margin-top:3.1pt; margin-bottom:0pt; text-align:justify; line-height:normal; font-family:'Verdana'; font-size:10pt }\r\n.Deltagare { margin-top:0pt; margin-bottom:0pt; text-align:justify; page-break-inside:avoid; page-break-after:avoid; line-height:9.5pt; font-family:'Verdana'; font-size:9.5pt }\r\n.Diagram-R { margin-top:12pt; margin-bottom:3pt; text-align:left; page-break-inside:avoid; page-break-after:avoid; line-height:10pt; font-family:'Verdana'; font-size:9pt; font-weight:bold }\r\n.Diagram-Rubrik { margin-top:12pt; margin-bottom:3pt; text-align:left; page-break-inside:avoid; page-break-after:avoid; line-height:10pt; font-family:'Verdana'; font-size:9pt; font-weight:bold }\r\n.Diagram-Underrubrik { margin-top:0pt; margin-bottom:1pt; text-align:left; page-break-inside:avoid; page-break-after:avoid; line-height:8pt; font-family:'Verdana'; font-size:8pt; font-weight:normal; font-style:italic }\r\n.DokumentRubrik { margin-top:6pt; margin-bottom:24pt; text-align:left; line-height:normal; border-bottom:0.75pt solid #000000; padding-bottom:4pt; font-family:'Verdana'; font-size:18pt; -aw-border-bottom:0.5pt single }\r\n.Dokumentbeteckning { margin-top:0pt; margin-bottom:0pt; text-align:left; page-break-inside:avoid; page-break-after:avoid; line-height:12.5pt; font-family:'Verdana'; font-size:16pt }\r\n.Fluglort { margin-top:0.1pt; margin-bottom:0pt; text-align:justify; line-height:0.7pt; font-family:'Verdana'; font-size:9.5pt }\r\n.Footer { margin-top:3.1pt; margin-bottom:0pt; text-align:justify; line-height:normal; font-family:'Verdana'; font-size:9.5pt }\r\n.FootnoteText { margin-top:0pt; margin-bottom:0pt; text-align:justify; line-height:8pt; font-family:'Verdana'; font-size:8pt }\r\n.Fotnotstextindrag { margin-top:0pt; margin-left:5.65pt; margin-bottom:0pt; text-align:left; line-height:8pt; font-family:'Verdana'; font-size:8pt }\r\n.Frslagspunkt { margin-top:0pt; margin-bottom:0pt; text-align:left; page-break-inside:avoid; page-break-after:avoid; line-height:12.5pt; font-family:'Verdana'; font-size:9.5pt; font-weight:bold }\r\n.Frslagstext { margin-top:0pt; margin-bottom:0pt; text-align:justify; line-height:12.5pt; font-family:'Verdana'; font-size:9.5pt }\r\n.Frteckningsrubrik { margin-top:9.6pt; margin-bottom:3.1pt; text-align:left; page-break-inside:avoid; page-break-after:avoid; line-height:normal; font-family:'Verdana'; font-size:9.5pt; font-weight:normal; font-style:italic; color:#000000 }\r\n.Grupprubrik { margin-top:6pt; margin-bottom:0pt; text-align:left; page-break-inside:avoid; page-break-after:avoid; line-height:12.5pt; font-family:'Verdana'; font-size:9.5pt; font-style:italic }\r\n.Grupprubrikindrag { margin-top:6pt; margin-left:22.1pt; margin-bottom:0pt; text-align:left; page-break-inside:avoid; page-break-after:avoid; line-height:12.5pt; font-family:'Verdana'; font-size:9.5pt; font-style:italic }\r\n.Header { margin-top:0pt; margin-bottom:0pt; text-align:justify; line-height:normal; font-family:'Verdana'; font-size:7.5pt; font-variant:small-caps }\r\n.Innehllsfrteckning { margin-top:0pt; margin-bottom:17.7pt; text-align:left; page-break-before:always; page-break-after:auto; line-height:normal; font-family:'Verdana'; font-size:16pt }\r\n.Kanslikommentar { margin-top:3.1pt; margin-bottom:12pt; text-align:left; page-break-after:avoid; line-height:12.5pt; font-family:'Verdana'; font-size:16pt }\r\n.Kantrubrik { margin-top:0pt; margin-bottom:0pt; text-align:justify; line-height:normal; font-family:'Verdana'; font-size:7.5pt }\r\n.ListBullet { margin-top:6.25pt; margin-left:17.85pt; margin-bottom:6.25pt; text-indent:-17.85pt; text-align:justify; line-height:12.5pt; font-family:'Verdana'; font-size:9.5pt }\r\n.ListParagraph { margin-top:3.1pt; margin-left:28.35pt; margin-bottom:0pt; text-align:justify; line-height:12.5pt; font-family:'Verdana'; font-size:9.5pt }\r\n.Litentext { margin-top:0pt; margin-bottom:0pt; text-align:justify; line-height:normal; font-family:'Verdana'; font-size:8pt }\r\n.Mellanrubrik { margin-top:11pt; margin-bottom:3.1pt; text-align:left; page-break-after:avoid; line-height:12.5pt; font-family:'Verdana'; font-size:9.5pt; font-style:italic }\r\n.Mellanrubrikverst { margin-top:0pt; margin-bottom:3.1pt; text-align:left; page-break-after:avoid; line-height:normal; font-family:'Verdana'; font-size:9.5pt; font-style:italic }\r\n.Mellanrum { margin-top:0pt; margin-bottom:0pt; text-align:left; page-break-before:auto; page-break-after:auto; line-height:1pt; widows:0; orphans:0; font-family:'Verdana'; font-size:1pt; font-variant:small-caps; text-decoration:none; color:#ffffff }\r\n.MotionsTypMarkering { margin-top:0pt; margin-bottom:0pt; text-align:right; line-height:12.5pt; font-family:'Verdana'; font-size:9.5pt; font-weight:bold }\r\n.NormalIndent { margin-top:0pt; margin-bottom:0pt; text-indent:11.35pt; text-align:justify; line-height:12.5pt; font-family:'Verdana'; font-size:9.5pt }\r\n.Normalinskjuten { margin-top:0pt; margin-left:22.1pt; margin-bottom:0pt; text-align:justify; line-height:12.5pt; font-family:'Verdana'; font-size:9.5pt }\r\n.Normalinskjutenindrag { margin-top:0pt; margin-left:22.1pt; margin-bottom:0pt; text-indent:11.35pt; text-align:justify; line-height:12.5pt; font-family:'Verdana'; font-size:9.5pt }\r\n.Normalinskjutenkursiv { margin-top:6pt; margin-bottom:0pt; line-height:normal; font-family:'Verdana'; font-size:10pt; font-style:italic }\r\n.Normalkursiv { margin-top:3.1pt; margin-bottom:0pt; text-align:left; line-height:12.5pt; font-family:'Verdana'; font-size:9.5pt; font-style:italic }\r\n.Normalruta { margin:3.1pt 5.65pt 0pt; text-align:justify; page-break-inside:avoid; page-break-after:avoid; line-height:12.5pt; border:0.75pt solid #000000; padding:4pt; font-family:'Verdana'; font-size:10.5pt; -aw-border:0.5pt single }\r\n.Normalrutafet { margin:3.1pt 5.65pt 0pt; text-align:justify; page-break-inside:avoid; page-break-after:avoid; line-height:12.5pt; border:0.75pt solid #000000; padding:4pt; font-family:'Verdana'; font-size:10.5pt; font-weight:bold; -aw-border:0.5pt single }\r\n.Normalrutaindrag { margin:0pt 5.65pt; text-indent:11.35pt; text-align:justify; page-break-inside:avoid; page-break-after:avoid; line-height:12.5pt; border:0.75pt solid #000000; padding:4pt; font-family:'Verdana'; font-size:10.5pt; -aw-border:0.5pt single }\r\n.Normalutanluftfre { margin-top:0pt; margin-bottom:0pt; text-align:justify; line-height:12.5pt; font-family:'Verdana'; font-size:9.5pt }\r\n.NormalLeft { margin-top:3.1pt; margin-bottom:0pt; text-align:left; line-height:12.5pt; font-family:'Verdana'; font-size:9.5pt }\r\n.NormalNoll { margin-top:0pt; margin-bottom:3.1pt; text-align:left; line-height:12.5pt; font-family:'Verdana'; font-size:10.5pt; font-weight:bold }\r\n.NumlistaTOC { margin:3.1pt 28.35pt 0pt 0pt; text-indent:0pt; text-align:left; line-height:normal; font-family:'Verdana'; font-size:9.5pt }\r\n.Ordfranden { margin-top:3.1pt; margin-bottom:22pt; text-align:left; page-break-inside:avoid; page-break-after:avoid; line-height:normal; font-family:'Verdana'; font-size:9.5pt; font-style:italic }\r\n.OrtochDatum { margin-top:18pt; margin-bottom:18pt; text-align:left; page-break-inside:avoid; page-break-after:avoid; line-height:normal; font-family:'Verdana'; font-size:9.5pt }\r\n.Punktlistabomb { margin-top:6.25pt; margin-left:14.2pt; margin-bottom:6.25pt; text-indent:-14.2pt; text-align:justify; line-height:12.5pt; font-family:'Verdana'; font-size:9.5pt }\r\n.Punktlistagemener { margin-top:6.25pt; margin-left:14.2pt; margin-bottom:6.25pt; text-indent:-14.2pt; text-align:justify; line-height:12.5pt; font-family:'Verdana'; font-size:9.5pt }\r\n.Punktlistalinje { margin-top:6.25pt; margin-left:14.2pt; margin-bottom:6.25pt; text-indent:-14.2pt; text-align:justify; line-height:12.5pt; font-family:'Verdana'; font-size:9.5pt }\r\n.Punktlistalinjeindragen { margin-top:6.25pt; margin-left:28.4pt; margin-bottom:6.25pt; text-indent:-14.2pt; text-align:justify; line-height:12.5pt; font-family:'Verdana'; font-size:9.5pt }\r\n.Punktlistasiffra { margin-top:6.25pt; margin-left:14.2pt; margin-bottom:6.25pt; text-indent:-14.2pt; text-align:justify; line-height:12.5pt; font-family:'Verdana'; font-size:9.5pt }\r\n.PVgnar { margin-top:3.1pt; margin-bottom:26pt; text-align:left; page-break-inside:avoid; page-break-after:avoid; line-height:normal; font-family:'Verdana'; font-size:9.5pt }\r\n.Quote { margin-top:6.1pt; margin-left:14.2pt; margin-bottom:0pt; text-align:justify; line-height:10pt; font-family:'Verdana'; font-size:9.5pt }\r\n.R1 { margin-top:3.1pt; margin-bottom:12pt; text-align:left; page-break-after:avoid; line-height:12.5pt; font-family:'Verdana'; font-size:16pt }\r\n.R1bilaga { margin-top:3.1pt; margin-bottom:12pt; text-align:left; page-break-after:auto; line-height:12.5pt; font-family:'Verdana'; font-size:16pt }\r\n.R2 { margin-top:20pt; margin-bottom:6pt; text-align:left; page-break-inside:avoid; page-break-after:avoid; line-height:12.5pt; font-family:'Verdana'; font-size:13.5pt }\r\n.R3 { margin-top:20pt; margin-bottom:3.1pt; text-align:left; page-break-inside:avoid; page-break-after:avoid; line-height:12.5pt; font-family:'Verdana'; font-size:10.5pt; font-weight:bold }\r\n.R4 { margin-top:15pt; margin-bottom:3.1pt; text-align:left; page-break-inside:avoid; page-break-after:avoid; line-height:12.5pt; font-family:'Verdana'; font-size:10.5pt; font-weight:normal; font-style:italic; color:#000000 }\r\n.R5 { margin-top:6.25pt; margin-bottom:0pt; text-align:left; page-break-inside:avoid; page-break-after:avoid; line-height:12.5pt; font-family:'Verdana'; font-size:9.5pt; font-weight:bold }\r\n.R6 { margin-top:6.25pt; margin-bottom:0pt; text-align:left; page-break-inside:avoid; page-break-after:avoid; line-height:12.5pt; font-family:'Verdana'; font-size:9.5pt; font-weight:normal; font-style:italic; color:#000000 }\r\n.Reservationshnvisning { margin-top:0pt; margin-bottom:8pt; text-align:right; line-height:12.5pt; font-family:'Verdana'; font-size:9.5pt; font-style:italic }\r\n.Reservationsrubrik { margin-top:0pt; margin-bottom:3.1pt; text-align:left; page-break-inside:avoid; page-break-after:avoid; line-height:12.5pt; font-family:'Verdana'; font-size:10.5pt; font-weight:bold }\r\n.Rubrik1Dokumentinformation { margin-top:0pt; margin-bottom:0pt; text-align:left; page-break-inside:avoid; page-break-after:avoid; line-height:12.5pt; font-family:'Verdana'; font-size:16pt }\r\n.Rubrik1bilaga { margin-top:0pt; margin-bottom:27.7pt; text-align:left; page-break-after:auto; line-height:12.5pt; font-family:'Verdana'; font-size:16pt }\r\n.Rubrik1medsidhuvud { margin-top:3.1pt; margin-bottom:12pt; text-align:left; page-break-before:always; page-break-after:avoid; line-height:12.5pt; font-family:'Verdana'; font-size:16pt }\r\n.Rubrik1numrerat { margin-top:3.1pt; margin-left:0pt; margin-bottom:12pt; text-indent:0pt; text-align:left; page-break-after:avoid; line-height:12.5pt; font-family:'Verdana'; font-size:16pt }\r\n.Rubrik1numreratmedsidhuvud { margin-top:0pt; margin-left:0pt; margin-bottom:16pt; text-indent:0pt; text-align:left; page-break-before:always; page-break-after:avoid; line-height:normal; font-family:'Verdana'; font-size:16pt }\r\n.Rubrik2bilaga { margin-top:20pt; margin-bottom:6pt; text-align:left; page-break-inside:avoid; page-break-after:avoid; line-height:12.5pt; font-family:'Verdana'; font-size:13.5pt }\r\n.Rubrik2numrerat { margin-top:20pt; margin-left:0pt; margin-bottom:6pt; text-indent:0pt; text-align:left; page-break-inside:avoid; page-break-after:avoid; line-height:12.5pt; font-family:'Verdana'; font-size:13.5pt }\r\n.Rubrik3numrerat { margin-top:20pt; margin-left:0pt; margin-bottom:3.1pt; text-indent:0pt; text-align:left; page-break-inside:avoid; page-break-after:avoid; line-height:12.5pt; font-family:'Verdana'; font-size:10.5pt; font-weight:bold }\r\n.Sammanfattning { margin-top:3.1pt; margin-bottom:12pt; text-align:left; page-break-after:auto; line-height:12.5pt; font-family:'Verdana'; font-size:16pt }\r\n.Sidhuvudhgerstlld { margin-top:0pt; margin-bottom:0pt; text-align:right; line-height:normal; font-family:'Verdana'; font-size:7.5pt; font-variant:small-caps }\r\n.Sidhuvudvnsterstlld { margin-top:0pt; margin-bottom:0pt; text-align:left; line-height:normal; font-family:'Verdana'; font-size:7.5pt; font-variant:small-caps }\r\n.Stdrubrik { margin-top:12pt; margin-bottom:0pt; line-height:12pt; font-family:'Verdana'; font-size:9.5pt; font-weight:bold }\r\n.Srskiltyttranderubrik { margin-top:0pt; margin-bottom:3.1pt; text-align:left; page-break-inside:avoid; page-break-after:avoid; line-height:12.5pt; font-family:'Verdana'; font-size:10.5pt; font-weight:bold }\r\n.TOC1 { margin-top:0pt; margin-right:28.35pt; margin-bottom:0pt; text-align:left; line-height:normal; font-family:'Verdana'; font-size:9.5pt }\r\n.TOC2 { margin:0pt 28.35pt 0pt 5.65pt; text-align:left; line-height:normal; font-family:'Verdana'; font-size:9.5pt }\r\n.TOC3 { margin:0pt 28.35pt 0pt 11.35pt; text-align:left; line-height:normal; font-family:'Verdana'; font-size:9.5pt }\r\n.TOC4 { margin:0pt 28.35pt 0pt 17pt; text-align:left; line-height:normal; font-family:'Verdana'; font-size:9.5pt }\r\n.TOC5 { margin:0pt 28.35pt 0pt 22.7pt; text-align:left; line-height:normal; font-family:'Verdana'; font-size:9.5pt }\r\n.TOC6 { margin-top:0pt; margin-left:47.65pt; margin-bottom:0pt; text-align:left; line-height:normal; font-family:'Verdana'; font-size:9.5pt }\r\n.TOC7 { margin-top:0pt; margin-right:28.35pt; margin-bottom:0pt; text-align:left; line-height:normal; font-family:'Verdana'; font-size:9.5pt }\r\n.TOC8 { margin-top:0pt; margin-right:28.35pt; margin-bottom:0pt; text-align:left; line-height:normal; font-family:'Verdana'; font-size:9.5pt }\r\n.TOC9 { margin-top:0pt; margin-left:8.5pt; margin-bottom:0pt; text-align:left; line-height:normal; font-family:'Verdana'; font-size:9.5pt }\r\n.TOCHeading { margin-top:3.1pt; margin-bottom:9pt; text-align:left; page-break-before:always; page-break-inside:avoid; page-break-after:avoid; line-height:12.5pt; font-family:'Verdana'; font-size:16pt }\r\n.Tabell-Kolumnrubrik { margin-top:3pt; margin-bottom:0pt; line-height:10pt; font-family:'Verdana'; font-size:8pt; font-weight:bold }\r\n.Tabell-KolumnrubrikHger { margin-top:3pt; margin-bottom:0pt; text-align:right; line-height:10pt; font-family:'Verdana'; font-size:8pt; font-weight:bold }\r\n.Tabell-Klla { margin-top:2pt; margin-bottom:0pt; line-height:8pt; font-family:'Verdana'; font-size:7pt }\r\n.Tabell-R { margin-top:12pt; margin-bottom:3pt; text-align:left; page-break-inside:avoid; page-break-after:avoid; line-height:10pt; font-family:'Verdana'; font-size:9pt; font-weight:bold }\r\n.Tabell-Radrubrik { margin-top:3pt; margin-bottom:0pt; line-height:10pt; font-family:'Verdana'; font-size:8pt }\r\n.Tabell-Rubrik { margin-top:12pt; margin-bottom:3pt; text-align:left; page-break-inside:avoid; page-break-after:avoid; line-height:10pt; font-family:'Verdana'; font-size:9pt; font-weight:bold }\r\n.Tabell-Siffror { margin-top:3pt; margin-bottom:0pt; text-align:right; line-height:10pt; font-family:'Verdana'; font-size:8pt }\r\n.Tabell-Text { margin-top:3pt; margin-bottom:0pt; line-height:10pt; font-family:'Verdana'; font-size:8pt }\r\n.Tabell-Underrubrik { margin-top:0pt; margin-bottom:1pt; text-align:left; page-break-inside:avoid; page-break-after:avoid; line-height:8pt; font-family:'Verdana'; font-size:8pt; font-weight:normal; font-style:italic }\r\n.TableofFigures { margin-top:3.1pt; margin-bottom:0pt; text-align:justify; line-height:normal; font-family:'Verdana'; font-size:9.5pt }\r\n.TillX-utskottet { margin-top:0pt; margin-bottom:12pt; text-align:left; page-break-after:avoid; line-height:12.5pt; font-family:'Verdana'; font-size:16pt }\r\n.Title { margin-top:3.1pt; margin-bottom:1pt; text-align:left; line-height:12pt; font-family:'Verdana'; font-size:20pt; letter-spacing:-0.5pt }\r\n.Vapen { margin-top:0pt; margin-bottom:0pt; text-align:left; page-break-inside:avoid; page-break-after:avoid; line-height:12.5pt; font-family:'Verdana'; font-size:16pt }\r\n.Yrkandelista { margin-top:3.1pt; margin-left:28.35pt; margin-bottom:0pt; text-indent:-28.35pt; text-align:justify; line-height:12.5pt; font-family:'Verdana'; font-size:9.5pt }\r\n.YrkandelistaEtt { margin-top:3.1pt; margin-left:0pt; margin-bottom:0pt; text-indent:0pt; text-align:justify; line-height:12.5pt; font-family:'Verdana'; font-size:9.5pt }\r\nspan.BallongtextChar { font-family:Tahoma; font-size:8pt }\r\nspan.BilagaChar { font-family:'Verdana'; font-size:8pt; font-variant:small-caps; text-decoration:underline }\r\nspan.BrdtextChar { font-family:'Verdana'; font-size:9.5pt }\r\nspan.BrdtextChar1 { font-family:'Verdana'; font-size:9.5pt }\r\nspan.Brdtextmedindrag2Char { font-family:'Verdana'; font-size:9.5pt }\r\nspan.CitatChar { font-family:'Verdana'; font-size:9.5pt }\r\nspan.DokumentRubrikChar { font-family:'Verdana'; font-size:18pt }\r\nspan.FotnotstextChar { font-family:'Verdana'; font-size:8pt }\r\nspan.FotnotstextindragChar { font-family:'Verdana'; font-size:8pt }\r\nspan.FrslagspunktChar { font-family:'Verdana'; font-size:9.5pt; font-weight:bold; font-style:normal }\r\nspan.Hyperlink { text-decoration:none; color:#000000; -aw-style-name:hyperlink }\r\nspan.KommentarerChar { font-family:'Verdana'; font-size:10pt }\r\nspan.NormalkursivChar { font-family:'Verdana'; font-size:9.5pt; font-style:italic }\r\nspan.NormaltindragChar { font-family:'Verdana'; font-size:9.5pt }\r\nspan.OrdfrandenChar { font-family:'Verdana'; font-size:9.5pt; font-style:italic }\r\nspan.OrtochDatumChar { font-family:'Verdana'; font-size:9.5pt }\r\nspan.PlaceholderText { color:#808080 }\r\nspan.PVgnarChar { font-family:'Verdana'; font-size:9.5pt }\r\nspan.ReservationshnvisningChar { font-family:'Verdana'; font-size:9.5pt; font-style:italic }\r\nspan.Rubrik1Char { font-family:'Verdana'; font-size:16pt }\r\nspan.Rubrik1DokumentinformationChar { font-family:'Verdana'; font-size:16pt }\r\nspan.Rubrik2Char { font-family:'Verdana'; font-size:13.5pt }\r\nspan.Rubrik3Char { font-family:'Verdana'; font-size:10.5pt; font-weight:bold }\r\nspan.Rubrik4Char { font-family:'Verdana'; font-size:10.5pt; font-style:italic; color:#000000 }\r\nspan.Rubrik5Char { font-family:'Verdana'; font-size:9.5pt; font-weight:bold }\r\nspan.Rubrik6Char { font-family:'Verdana'; font-size:9.5pt; font-style:italic; color:#000000 }\r\nspan.Rubrik7Char { font-family:'Verdana'; font-size:9.5pt; font-style:italic; color:#243f60 }\r\nspan.Rubrik8Char { font-family:'Verdana'; font-size:9pt; color:#272727 }\r\nspan.Rubrik9Char { font-family:'Verdana'; font-size:9pt; font-style:italic; color:#272727 }\r\nspan.RubrikChar { font-family:'Verdana'; font-size:20pt; letter-spacing:-0.5pt }\r\nspan.SidfotChar { font-family:'Verdana'; font-size:9.5pt }\r\nspan.SidhuvudChar { font-family:'Verdana'; font-size:7.5pt; font-variant:small-caps }\r\nspan.Tabell-Upphjttecken { font-family:'Verdana'; font-variant:normal; text-decoration:none; text-transform:none; vertical-align:super; display:inline }\r\nspan.VapenChar { font-family:'Verdana'; font-size:16pt }\r\nspan.tBilagaJA { color:#000000 }\r\nspan.tSidrubrikJA { color:#000000 }\r\n.PlainTable1 {  }\r\n.TableGrid {  }\r\n--></style>\r\n\r\n\t\t<div class=\"Section1\">\r\n\t\t\t<table cellspacing=\"0\" cellpadding=\"0\" style=\"margin-top:0pt; border-collapse:collapse\">\r\n\t\t\t\t<tr style=\"height:79.4pt; -aw-height-rule:exactly\">\r\n\t\t\t\t\t<td style=\"width:297.7pt; vertical-align:top\">\r\n\t\t\t\t\t\t<p class=\"Rubrik1Dokumentinformation\" style=\"line-height:16pt\">\r\n\t\t\t\t\t\t\t<a name=\"_Hlk213170018\"><span style=\"-aw-sdt-tag:'ccUtskott'; -aw-sdt-title:'utskottsnamn Dokumentegenskap'\"><span>Socialförsäkringsutskottet</span></span><span style=\"-aw-sdt-tag:'ccS'; -aw-sdt-title:'s'\"><span>s</span></span><span style=\"-aw-sdt-tag:'ccMellanslag'; -aw-sdt-title:'Mellanslag'\"><span style=\"-aw-import:spaces\">&#xa0;</span></span></a><a name=\"Utlatande\"></a><span>betänkande</span>\r\n\t\t\t\t\t\t</p>\r\n\t\t\t\t\t\t<p class=\"Dokumentbeteckning\" style=\"line-height:16pt\">\r\n\t\t\t\t\t\t\t<span style=\"-aw-sdt-tag:'ccRiksmote'; -aw-sdt-title:'riksmote Dokumentegenskap'\"><span>2025/26</span></span><span style=\"-aw-sdt-tag:'ccKolon'; -aw-sdt-title:'Kolon'\"><span>:</span></span><a name=\"Utskottebeteckning\"></a><span>SfU8 </span>\r\n\t\t\t\t\t\t</p>\r\n\t\t\t\t\t\t<p class=\"Rubrik1Dokumentinformation\" style=\"line-height:16pt\">\r\n\t\t\t\t\t\t\t<span style=\"-aw-import:ignore\">&#xa0;</span>\r\n\t\t\t\t\t\t</p>\r\n\t\t\t\t\t</td>\r\n\t\t\t\t</tr>\r\n\t\t\t</table>\r\n\t\t\t<div style=\"-aw-sdt-tag:'ccDokumentrubrik'; -aw-sdt-title:'dokumentrubrik Dokumentegenskap'\">\r\n\t\t\t\t<p class=\"DokumentRubrik\">\r\n\t\t\t\t\t<span>Riksrevisionens rapport om Migrationsverkets hantering av medborgarskapsärenden</span>\r\n\t\t\t\t</p>\r\n\t\t\t</div>\r\n\t\t\t<p class=\"Sammanfattning\" style=\"line-height:16pt\">\r\n\t\t\t\t<span class=\"tSidrubrikJA\">Sammanfattning</span>\r\n\t\t\t</p>\r\n\t\t\t<p style=\"widows:0; orphans:0\">\r\n\t\t\t\t<span>Utskottet föreslår att riksdagen lägger regeringens skrivelse Riksrevisionens rapport om Migrationsverkets hantering av medborgarskapsärenden till hand</span><span>&#xad;</span><span>lingarna.</span>\r\n\t\t\t</p>\r\n\t\t\t<p class=\"NormalIndent\">\r\n\t\t\t\t<span>I skrivelsen redogör regeringen för sin bedömning av de iakttagelser som Riksrevisionen har gjort och de rekommendationer som den riktar till reger</span><span>&#xad;</span><span>ingen i rapporten Migrationsverkets hantering av medborgarskapsärenden (RiR 2025:5) samt de åtgärder som regeringen har vidtagit med anledning bl.a. av de brister som Riksrevisionen har lyft fram i rapporten.</span>\r\n\t\t\t</p>\r\n\t\t\t<p class=\"NormalIndent\">\r\n\t\t\t\t<span>I betänkandet finns ett särskilt yttrande (S).</span>\r\n\t\t\t</p>\r\n\t\t\t<p class=\"R4\">\r\n\t\t\t\t<span>Behandlade förslag</span>\r\n\t\t\t</p>\r\n\t\t\t<p>\r\n\t\t\t\t<span>Skrivelse 2025/26:9 Riksrevisionens rapport om Migrationsverkets hantering av medborgarskapsärenden.</span>\r\n\t\t\t</p>\r\n\t\t\t<p class=\"Innehllsfrteckning\">\r\n\t\t\t\t<a name=\"Innehållsförteckning\"></a><span class=\"tSidrubrikJA\">Innehållsförteckning</span>\r\n\t\t\t</p>\r\n\t\t\t<p class=\"TOC1\">\r\n\t\t\t\t<a href=\"#_Toc219275391\" style=\"text-decoration:none\"><span class=\"Hyperlink\">Utskottets förslag till riksdagsbeslut</span></a>\r\n\t\t\t</p>\r\n\t\t\t<p class=\"TOC1\">\r\n\t\t\t\t<a href=\"#_Toc219275392\" style=\"text-decoration:none\"><span class=\"Hyperlink\">Redogörelse för ärendet</span></a>\r\n\t\t\t</p>\r\n\t\t\t<p class=\"TOC1\">\r\n\t\t\t\t<a href=\"#_Toc219275393\" style=\"text-decoration:none\"><span class=\"Hyperlink\">Utskottets överväganden</span></a>\r\n\t\t\t</p>\r\n\t\t\t<p class=\"TOC2\">\r\n\t\t\t\t<a href=\"#_Toc219275394\" style=\"text-decoration:none\"><span class=\"Hyperlink\">Riksrevisionens rapport om Migrationsverkets hantering av medborgarskapsärenden</span></a>\r\n\t\t\t</p>\r\n\t\t\t<p class=\"TOC1\">\r\n\t\t\t\t<a href=\"#_Toc219275395\" style=\"text-decoration:none\"><span class=\"Hyperlink\">Särskilt yttrande</span></a>\r\n\t\t\t</p>\r\n\t\t\t<p class=\"TOC7\" style=\"margin-left:5.65pt\">\r\n\t\t\t\t<a href=\"#_Toc219275396\" style=\"text-decoration:none\"><span class=\"Hyperlink\">Regeringens skrivelse (S)</span></a>\r\n\t\t\t</p>\r\n\t\t\t<p class=\"TOC8\">\r\n\t\t\t\t<span class=\"Hyperlink\" style=\"font-style:italic\">Bilaga</span><br><a href=\"#_Toc219275397\" style=\"text-decoration:none\"><span class=\"Hyperlink\">Förteckning över behandlade förslag</span></a>\r\n\t\t\t</p>\r\n\t\t\t<p class=\"TOC9\">\r\n\t\t\t\t<a href=\"#_Toc219275398\" style=\"text-decoration:none\"><span class=\"Hyperlink\">Skrivelsen</span></a>\r\n\t\t\t</p>\r\n\t\t\t<p class=\"Fluglort\">\r\n\t\t\t</p>\r\n\t\t\t<p class=\"Fluglort\">\r\n\t\t\t\t<span style=\"-aw-import:ignore\">&#xa0;</span>\r\n\t\t\t</p>\r\n\t\t\t<p class=\"Avsnittsrubrik\">\r\n\t\t\t\t<a name=\"_Toc219275391\"></a><a name=\"StopCC\"></a><span class=\"tSidrubrikJA\">Utskottets förslag till riksdagsbeslut</span><span style=\"-aw-bookmark-end:_Toc219275391\"></span>\r\n\t\t\t</p>\r\n\t\t\t<div style=\"-aw-sdt-tag:'dokumentavsnitt/utskottets förslag till riksdagsbeslut/1809816316/1768309370708'; -aw-sdt-title:'utskottets förslag till riksdagsbeslut'\">\r\n\t\t\t\t<p class=\"Mellanrum\">\r\n\t\t\t\t\t<span style=\"-aw-import:spaces\">&#xa0;</span>\r\n\t\t\t\t</p>\r\n\t\t\t\t<p class=\"Mellanrum\">\r\n\t\t\t\t\t<span style=\"-aw-import:spaces\">&#xa0;</span>\r\n\t\t\t\t</p>\r\n\t\t\t\t<table cellspacing=\"0\" cellpadding=\"0\" style=\"width:294.2pt; margin-top:0pt; border-collapse:collapse\">\r\n\t\t\t\t\t<tr style=\"page-break-inside:avoid\">\r\n\t\t\t\t\t\t<td style=\"width:22pt; vertical-align:top\">\r\n\t\t\t\t\t\t\t<p class=\"NormalLeft\" style=\"page-break-inside:avoid; page-break-after:avoid\">\r\n\t\t\t\t\t\t\t\t<span style=\"font-size:10.5pt; font-weight:bold\">Regeringens skrivelse</span>\r\n\t\t\t\t\t\t\t</p>\r\n\t\t\t\t\t\t</td>\r\n\t\t\t\t\t</tr>\r\n\t\t\t\t</table>\r\n\t\t\t\t<p class=\"Normalutanluftfre\">\r\n\t\t\t\t\t<span>Riksdagen lägger skrivelse 2025/26:9 till handlingarna.</span>\r\n\t\t\t\t</p>\r\n\t\t\t\t<p class=\"Mellanrum\">\r\n\t\t\t\t\t<span style=\"-aw-import:ignore\">&#xa0;</span>\r\n\t\t\t\t</p>\r\n\t\t\t\t<p class=\"OrtochDatum\">\r\n\t\t\t\t\t<span>Stockholm den 13 januari 2026</span>\r\n\t\t\t\t</p>\r\n\t\t\t\t<p class=\"PVgnar\">\r\n\t\t\t\t\t<span>På socialförsäkringsutskottets vägnar</span>\r\n\t\t\t\t</p>\r\n\t\t\t\t<p class=\"Ordfranden\">\r\n\t\t\t\t\t<span>Viktor Wärnick</span>\r\n\t\t\t\t</p>\r\n\t\t\t\t<p class=\"Deltagare\">\r\n\t\t\t\t\t<span>Följande ledamöter har deltagit i beslutet: Viktor Wärnick (M), Ludvig Aspling (SD), Ida Karkiainen (S), Sanne Lennström (S), Clara Aranda (SD), Jessica Rodén (S), Ulrika Heindorff (M), Åsa Eriksson (S), Daniel Persson (SD), Magnus Resare (M), Ingemar Kihlström (KD), Nima Gholam Ali Pour (SD), Malte Tängmark Roos (MP), Patrik Karlson (L), Arber Gashi (S), Maj Karlsson (V) och Madeleine Atlas (C).</span>\r\n\t\t\t\t</p>\r\n\t\t\t\t<p class=\"Mellanrum\">\r\n\t\t\t\t\t<span style=\"-aw-import:ignore\">&#xa0;</span>\r\n\t\t\t\t</p>\r\n\t\t\t\t<p class=\"Mellanrum\">\r\n\t\t\t\t\t<span style=\"-aw-import:ignore\">&#xa0;</span>\r\n\t\t\t\t</p>\r\n\t\t\t\t<p class=\"Mellanrum\">\r\n\t\t\t\t\t<span style=\"font-size:9.5pt; -aw-import:ignore\">&#xa0;</span>\r\n\t\t\t\t</p>\r\n\t\t\t</div>\r\n\t\t\t<p>\r\n\t\t\t\t<span style=\"-aw-import:ignore\">&#xa0;</span>\r\n\t\t\t</p>\r\n\t\t\t<p class=\"Avsnittsrubrik\">\r\n\t\t\t\t<a name=\"_Toc219275392\"></a><a name=\"SlutUtskottsForslag\"></a><span class=\"tSidrubrikJA\">Redogörelse för ärendet</span><span style=\"-aw-bookmark-end:_Toc219275392\"></span>\r\n\t\t\t</p>\r\n\t\t\t<p>\r\n\t\t\t\t<span>Riksrevisionen överlämnade den 25 mars 2025 rapporten Migrationsverkets hantering av medborgarskapsärenden (RiR 2025:5) till riksdagen. Samma dag överlämnade riksdagen i sin tur rapporten till regeringen. Regeringen återkom till riksdagen med skrivelse 2025/26:9 Riksrevisionens rapport om Migra</span><span>&#xad;</span><span>tionsverkets hantering av medborgarskapsärenden.</span>\r\n\t\t\t</p>\r\n\t\t\t<p class=\"NormalIndent\">\r\n\t\t\t\t<span>I detta betänkande behandlar utskottet regeringens skrivelse.</span>\r\n\t\t\t</p>\r\n\t\t\t<p class=\"NormalIndent\">\r\n\t\t\t\t<span>Riksrevisor Christina Gellerbrant Hagberg med medarbetare informerade om Riksrevisionens rapport vid socialförsäkringsutskottets sammanträde den 8 maj 2025. </span>\r\n\t\t\t</p>\r\n\t\t\t<p class=\"Avsnittsrubrik\">\r\n\t\t\t\t<a name=\"_Toc219275393\"><span class=\"tSidrubrikJA\">Utskottets överväganden</span></a>\r\n\t\t\t</p>\r\n\t\t\t<h2 style=\"line-height:13.5pt\">\r\n\t\t\t\t<a name=\"_Toc219275394\"><span>Riksrevisionens rapport om Migrationsverkets hantering av medborgarskapsärenden</span></a>\r\n\t\t\t</h2>\r\n\t\t\t<div style=\"margin-top:3.1pt; margin-right:0.9pt; margin-left:0.9pt; border:0.75pt solid #000000; -aw-border:0.5pt single; clear:both\">\r\n\t\t\t\t<p class=\"Normalrutafet\" style=\"margin-top:0pt; margin-right:0pt; margin-left:0pt; border-style:none; padding-bottom:0pt\">\r\n\t\t\t\t\t<span>Utskottets förslag i korthet</span>\r\n\t\t\t\t</p>\r\n\t\t\t\t<p class=\"Normalruta\" style=\"margin-top:0pt; margin-right:0pt; margin-left:0pt; border-style:none; padding-top:0pt; padding-bottom:0pt\">\r\n\t\t\t\t\t<span>Riksdagen lägger regeringens skrivelse till handlingarna.</span>\r\n\t\t\t\t</p>\r\n\t\t\t\t<div style=\"-aw-sdt-tag:'d471d7fa-7284-42c7-bb28-4569a7bb0e3e/förslagsrutor reservations text/-463944056/1764861647390'; -aw-sdt-title:'förslagsrutor reservations text'\">\r\n\t\t\t\t\t<p class=\"Normalrutaindrag\" style=\"margin-right:0pt; margin-left:0pt; border-style:none; padding-top:0pt\">\r\n\t\t\t\t\t\t<span>Jämför det särskilda yttrandet (S).</span>\r\n\t\t\t\t\t</p>\r\n\t\t\t\t</div>\r\n\t\t\t</div>\r\n\t\t\t<p class=\"R3\" style=\"margin-bottom:0pt\">\r\n\t\t\t\t<span>Regeringens skrivelse</span>\r\n\t\t\t</p>\r\n\t\t\t<p class=\"R4\" style=\"margin-top:6.25pt\">\r\n\t\t\t\t<span>Riksrevisionens iakttagelser och rekommendationer</span>\r\n\t\t\t</p>\r\n\t\t\t<p>\r\n\t\t\t\t<span>Granskningen fokuserar på om Migrationsverket arbetar effektivt för att säker</span><span>&#xad;</span><span>ställa korrekta beslut som fattas utan onödiga dröjsmål i medborgarskaps</span><span>&#xad;</span><span>ärenden. Riksrevisionen har även granskat verksamhetens måluppfyllelse och resurseffektivitet samt de förutsättningar som regeringen har gett Migrations</span><span>&#xad;</span><span>verket för att hantera ärendena. Riksrevisionen har särskilt inriktat sig på regeringens roll för verkets rättsliga förutsättningar till informationsutbyte med andra myndigheter samt konsekvenser av möjligheten till begäran om avgörande i förvaltningslagen (2017:900).</span>\r\n\t\t\t</p>\r\n\t\t\t<p class=\"NormalIndent\">\r\n\t\t\t\t<span>Riksrevisionens granskning omfattar perioden 2018–2023, vilket inklu</span><span>&#xad;</span><span>derar de år då det varit möjligt att lämna in en begäran om avgörande enligt förvaltningslagen.</span>\r\n\t\t\t</p>\r\n\t\t\t<p class=\"NormalIndent\">\r\n\t\t\t\t<span>Riksrevisionens övergripande bedömning är att Migrationsverkets hanter</span><span>&#xad;</span><span>ing av medborgarskapsärenden inte är effektiv, att myndigheten brister i vissa avseenden med att säkerställa korrekta beslut och att det finns en risk för att ärenden inte bedöms enhetligt. Riksrevisionen bedömer att handläggnings</span><span>&#xad;</span><span>tiderna är oskäligt långa i många medborgarskapsärenden och att det finns effektivitetsbrister i målstyrning och kvalitetsuppföljning. Ytterligare slutsat</span><span>&#xad;</span><span>ser är att det saknas rättsliga förutsättningar för effektiv informationsinhämt</span><span>&#xad;</span><span>ning från andra myndigheter och att regeringen inte vidtagit tillräckliga åtgär</span><span>&#xad;</span><span>der med anledning av de negativa konsekvenser som införandet av begäran om avgörande i förvaltningslagen fått för enskilda individer.</span>\r\n\t\t\t</p>\r\n\t\t\t<p class=\"NormalIndent\">\r\n\t\t\t\t<span>Riksrevisionen har lämnat följande rekommendationer till regeringen:</span>\r\n\t\t\t</p>\r\n\t\t\t<p class=\"Punktlistalinje\" style=\"margin-bottom:0pt; -aw-import:list-item; -aw-list-level-number:0; -aw-list-number-format:'–'; -aw-list-number-styles:'bullet'; -aw-list-padding-sml:9.2pt\">\r\n\t\t\t\t<span style=\"-aw-import:ignore\"><span style=\"font-size:10pt\">–</span><span style=\"width:9.2pt; font:7pt 'Verdana'; display:inline-block; -aw-import:spaces\">&#xa0;&#xa0;&#xa0;&#xa0;&#xa0; </span></span><span>Säkerställ att Migrationsverket har rättsliga förutsättningar att ta del av information från andra myndigheter som behövs för att handlägga med</span><span>&#xad;</span><span>borgarskapsärenden effektivt och med hög rättslig kvalitet. Det gäller exempelvis uppgifter från Skatteverket som behövs för bedömningen av hemvist och uppehållsrätt.</span>\r\n\t\t\t</p>\r\n\t\t\t<p class=\"Punktlistalinje\" style=\"margin-top:0pt; -aw-import:list-item; -aw-list-level-number:0; -aw-list-number-format:'–'; -aw-list-number-styles:'bullet'; -aw-list-padding-sml:9.2pt\">\r\n\t\t\t\t<span style=\"-aw-import:ignore\"><span style=\"font-size:10pt\">–</span><span style=\"width:9.2pt; font:7pt 'Verdana'; display:inline-block; -aw-import:spaces\">&#xa0;&#xa0;&#xa0;&#xa0;&#xa0; </span></span><span>Vidta åtgärder för att hantera negativa konsekvenser av möjligheten till begäran om avgörande i medborgarskapsärenden.</span>\r\n\t\t\t</p>\r\n\t\t\t<p>\r\n\t\t\t\t<span>Riksrevisionen har lämnat följande rekommendationer till Migrationsverket:</span>\r\n\t\t\t</p>\r\n\t\t\t<p class=\"Punktlistalinje\" style=\"margin-bottom:0pt; -aw-import:list-item; -aw-list-level-number:0; -aw-list-number-format:'–'; -aw-list-number-styles:'bullet'; -aw-list-padding-sml:9.2pt\">\r\n\t\t\t\t<span style=\"-aw-import:ignore\"><span style=\"font-size:10pt\">–</span><span style=\"width:9.2pt; font:7pt 'Verdana'; display:inline-block; -aw-import:spaces\">&#xa0;&#xa0;&#xa0;&#xa0;&#xa0; </span></span><span>Se över och utveckla myndighetens målstyrning, system för fördelning av ärenden och hantering av ärendebalanser. Detta i syfte att minimera oskä</span><span>&#xad;</span><span>ligt långa dröjsmål och säkerställa att det finns en plan för hantering av samtliga medborgarskapsärenden.</span>\r\n\t\t\t</p>\r\n\t\t\t<p class=\"Punktlistalinje\" style=\"margin-top:0pt; margin-bottom:0pt; -aw-import:list-item; -aw-list-level-number:0; -aw-list-number-format:'–'; -aw-list-number-styles:'bullet'; -aw-list-padding-sml:9.2pt\">\r\n\t\t\t\t<span style=\"-aw-import:ignore\"><span style=\"font-size:10pt\">–</span><span style=\"width:9.2pt; font:7pt 'Verdana'; display:inline-block; -aw-import:spaces\">&#xa0;&#xa0;&#xa0;&#xa0;&#xa0; </span></span><span>Utveckla fler inbyggda kontrollmekanismer i handläggningssystemet samt utveckla myndighetsgemensamma rutiner och stöd. Detta i syfte att främja enhetliga bedömningar mellan regionerna och säkerställa korrekta beslut i medborgarskapsärenden.</span>\r\n\t\t\t</p>\r\n\t\t\t<p class=\"Punktlistalinje\" style=\"margin-top:0pt; margin-bottom:0pt; -aw-import:list-item; -aw-list-level-number:0; -aw-list-number-format:'–'; -aw-list-number-styles:'bullet'; -aw-list-padding-sml:9.2pt\">\r\n\t\t\t\t<span style=\"-aw-import:ignore\"><span style=\"font-size:10pt\">–</span><span style=\"width:9.2pt; font:7pt 'Verdana'; display:inline-block; -aw-import:spaces\">&#xa0;&#xa0;&#xa0;&#xa0;&#xa0; </span></span><span>Utveckla uppföljningen av medborgarskapsprövningen avseende hand</span><span>&#xad;</span><span>läggningstider och rättslig kvalitet, särskilt när det gäller om nuvarande utredningsåtgärder är tillräckliga.</span>\r\n\t\t\t</p>\r\n\t\t\t<p class=\"Punktlistalinje\" style=\"margin-top:0pt; -aw-import:list-item; -aw-list-level-number:0; -aw-list-number-format:'–'; -aw-list-number-styles:'bullet'; -aw-list-padding-sml:9.2pt\">\r\n\t\t\t\t<span style=\"-aw-import:ignore\"><span style=\"font-size:10pt\">–</span><span style=\"width:9.2pt; font:7pt 'Verdana'; display:inline-block; -aw-import:spaces\">&#xa0;&#xa0;&#xa0;&#xa0;&#xa0; </span></span><span>Stärk erfarenhetsutbytet på central nivå mellan medborgarskapspröv</span><span>&#xad;</span><span>ningen och andra ärendeslag.</span>\r\n\t\t\t</p>\r\n\t\t\t<p class=\"R4\">\r\n\t\t\t\t<span>Regeringens bedömning och åtgärder med anledning av Riksrevisionens iakttagelser</span>\r\n\t\t\t</p>\r\n\t\t\t<p>\r\n\t\t\t\t<span>Regeringen instämmer delvis i Riksrevisionens rekommendationer. Reger</span><span>&#xad;</span><span>ingen anger att sedan den tillträdde har frågor om rättssäkerhet i migrations</span><span>&#xad;</span><span>processen och hanteringen av medborgarskapsärenden uppmärksammats genom flera åtgärder, inklusive ny lagstiftning och förstärkt styrning. Reger</span><span>&#xad;</span><span>ingen vidtog redan före Riksrevisionens granskningsrapport flera åtgärder i linje med de rekommendationer som nu lämnas. Det gäller särskilt förbättring av kontroller och säkerhetsåtgärder i medborgarskapsärenden samt utökade rättsliga förutsättningar för informationsutbyte mellan myndigheter.</span>\r\n\t\t\t</p>\r\n\t\t\t<p class=\"R5\">\r\n\t\t\t\t<span>Förutsättningar för korrekta beslut</span>\r\n\t\t\t</p>\r\n\t\t\t<p>\r\n\t\t\t\t<span>Regeringen har under 2024 och 2025 gett Migrationsverket ett flertal uppdrag som ska bidra till att stärka myndighetens förutsättningar att fatta korrekta beslut, bl.a. att stärka kontrollerna i medborgarskapsärenden, däribland identi</span><span>&#xad;</span><span>tetskontroller, och att tillsammans med andra myndigheter utreda och stärka samarbetet för att motverka identitetsmissbruk. Det handlar också om att med hjälp av digital teknik öka effektiviteten i verksamheten och informations</span><span>&#xad;</span><span>utbytet, både inom myndigheten och med andra myndigheter.</span>\r\n\t\t\t</p>\r\n\t\t\t<p class=\"NormalIndent\">\r\n\t\t\t\t<span>Vidare har möjligheten till informationsutbyte mellan myndigheter, både nationellt och internationellt, ökat genom olika lagändringar. Migrationsverket har också infört krav på personlig inställelse vid ansökan om medborgarskap.</span>\r\n\t\t\t</p>\r\n\t\t\t<p class=\"NormalIndent\">\r\n\t\t\t\t<span>Regeringen har därutöver tillsatt flera utredningar som på olika sätt ska bidra till att säkerställa korrekta beslut. Det handlar om skärpta krav för med</span><span>&#xad;</span><span>borgarskap i form av bl.a. krav på längre hemvisttid och ett hederligt levnads</span><span>&#xad;</span><span>sätt. Vidare gäller det ökade möjligheter för Skatteverket och Migrationsverket att lagra, behandla och dela biometriska uppgifter samt utökade möjligheter till informationsutbyte mellan myndigheter.</span>\r\n\t\t\t</p>\r\n\t\t\t<p class=\"R5\">\r\n\t\t\t\t<span>Handläggningstider</span>\r\n\t\t\t</p>\r\n\t\t\t<p>\r\n\t\t\t\t<span>När det gäller handläggningstiderna noterar regeringen att Migrationsverket beslutat att vidta flera åtgärder för att effektivisera handläggningen av medbor</span><span>&#xad;</span><span>garskapsärenden. Det handlar bl.a. om att tillföra ytterligare resurser till hand</span><span>&#xad;</span><span>läggningen av de äldre ärendena, handlägga ärenden i turordning samt se över om handläggningsprocessen kan förenklas och effektiviseras i ärenden om att ett medborgarskapsärende ska avgöras.</span>\r\n\t\t\t</p>\r\n\t\t\t<p class=\"NormalIndent\">\r\n\t\t\t\t<span>Regeringen konstaterar att de åtgärder som redovisas bidrar till att skapa bättre förutsättningar för att förkorta handläggningstiderna. Särskilt viktiga är effektiviseringsåtgärder såsom nya digitala lösningar, förbättrat informations</span><span>&#xad;</span><span>utbyte samt insatser för mer träffsäkra identitetsbedömningar i tillstånds</span><span>&#xad;</span><span>ärenden.</span>\r\n\t\t\t</p>\r\n\t\t\t<p class=\"R5\">\r\n\t\t\t\t<span>Regeringens samlade bedömning</span>\r\n\t\t\t</p>\r\n\t\t\t<p>\r\n\t\t\t\t<span>Genom skrivelsen anser regeringen att Riksrevisionens rapport är slut</span><span>&#xad;</span><span>behandlad.</span>\r\n\t\t\t</p>\r\n\t\t\t<p class=\"R3\">\r\n\t\t\t\t<span>Utskottets ställningstagande</span>\r\n\t\t\t</p>\r\n\t\t\t<p>\r\n\t\t\t\t<span>Riksrevisionen har i sin granskning funnit att Migrationsverkets hantering av medborgarskapsärenden inte är effektiv och har ett flertal brister, bl.a. när det gäller säkerställandet av att beslut som fattas är korrekta och handläggnings</span><span>&#xad;</span><span>tiderna. </span>\r\n\t\t\t</p>\r\n\t\t\t<p class=\"NormalIndent\">\r\n\t\t\t\t<span>Utskottet vill betona vikten av att besluten i medborgarskapsärendena är korrekta och fattas inom rimlig tid. Utskottet ser därför positivt på regeringens vidtagna och kommande åtgärder för att förbättra hanteringen av ärendena, bl.a. ny lagstiftning, förstärkt styrning och effektivisering.</span>\r\n\t\t\t</p>\r\n\t\t\t<p class=\"NormalIndent\">\r\n\t\t\t\t<span>Utskottet föreslår att riksdagen lägger skrivelsen till handlingarna.</span>\r\n\t\t\t</p>\r\n\t\t\t<p class=\"Avsnittsrubrik\">\r\n\t\t\t\t<a name=\"_Toc219275395\"><span class=\"tSidrubrikJA\">Särskilt yttrande</span></a>\r\n\t\t\t</p>\r\n\t\t\t<div style=\"-aw-sdt-tag:'1a6266da-d849-4d0f-b5c8-b8a5ab09b878/särskilda yttranden/-653328091/1768309373703'; -aw-sdt-title:'särskilda yttranden'\">\r\n\t\t\t\t<p class=\"Mellanrum\">\r\n\t\t\t\t\t<span style=\"-aw-import:spaces\">&#xa0;</span>\r\n\t\t\t\t</p>\r\n\t\t\t\t<table cellspacing=\"0\" cellpadding=\"0\" style=\"width:294.2pt; margin-top:0pt; border-collapse:collapse\">\r\n\t\t\t\t\t<tr style=\"page-break-inside:avoid\">\r\n\t\t\t\t\t\t<td style=\"vertical-align:top\">\r\n\t\t\t\t\t\t\t<p class=\"Srskiltyttranderubrik\">\r\n\t\t\t\t\t\t\t\t<a name=\"_Toc219275396\"><span>Regeringens skrivelse (S)</span></a>\r\n\t\t\t\t\t\t\t</p>\r\n\t\t\t\t\t\t</td>\r\n\t\t\t\t\t</tr>\r\n\t\t\t\t</table>\r\n\t\t\t\t<p style=\"page-break-inside:avoid; page-break-after:avoid\">\r\n\t\t\t\t\t<span>Ida Karkiainen (S), Sanne Lennström (S), Jessica Rodén (S), Åsa Eriksson (S) och Arber Gashi (S) anför:</span>\r\n\t\t\t\t</p>\r\n\t\t\t\t<p class=\"Mellanrum\">\r\n\t\t\t\t\t<span style=\"-aw-import:ignore\">&#xa0;</span>\r\n\t\t\t\t</p>\r\n\t\t\t</div>\r\n\t\t\t<p>\r\n\t\t\t\t<span>Socialdemokraterna har presenterat sin politik på migrationsområdet i motion 2025/26:3587. Förslagen innebär bl.a. att regeringen bör fokusera på att för</span><span>&#xad;</span><span>korta handläggningstiderna hos Migrationsverket. Myndigheten fick 2024 ett generellt sparkrav, vilket innebar att personalneddragningar fick genomföras. Detta ledde till kraftigt förlängda handläggningstider för medborgarskaps</span><span>&#xad;</span><span>ärendena, vilket skapar problem för enskilda. Därefter har anslagen ökat, men ryckigheten ger inte myndigheten rimliga förutsättningar att klara sina uppgif</span><span>&#xad;</span><span>ter. Eftersom vårt yrkande om handläggningstider i motion 2025/26:3587 kommer att behandlas i betänkande SfU16 Migrationsfrågor i vår har vi valt att inte lämna någon motion och reservera oss i detta betänkande.</span>\r\n\t\t\t</p>\r\n\t\t\t<p class=\"Bilaga\">\r\n\t\t\t\t<span class=\"tBilagaJA\" style=\"text-decoration:underline\">Bilaga</span>\r\n\t\t\t</p>\r\n\t\t\t<p class=\"Bilagerubrik\">\r\n\t\t\t\t<a name=\"_Toc219275397\"><span class=\"tSidrubrikJA\">Förteckning över behandlade förslag</span></a>\r\n\t\t\t</p>\r\n\t\t\t<div style=\"-aw-sdt-tag:'dokumentavsnitt/förteckning över behandlade förslag/-1131379093/1762187047649'; -aw-sdt-title:'förteckning över behandlade förslag'\">\r\n\t\t\t\t<p class=\"Rubrik2bilaga\" style=\"line-height:13.5pt\">\r\n\t\t\t\t\t<a name=\"_Toc219275398\"><span>Skrivelsen</span></a><span> </span>\r\n\t\t\t\t</p>\r\n\t\t\t\t<p>\r\n\t\t\t\t\t<span>Regeringens skrivelse 2025/26:9 Riksrevisionens rapport om Migrationsverkets hantering av medborgarskapsärenden.</span>\r\n\t\t\t\t</p>\r\n\t\t\t\t<p class=\"Mellanrum\">\r\n\t\t\t\t\t<span style=\"-aw-import:spaces\">&#xa0;</span>\r\n\t\t\t\t</p>\r\n\t\t\t\t<p class=\"Mellanrum\">\r\n\t\t\t\t\t<span style=\"-aw-import:ignore\">&#xa0;</span>\r\n\t\t\t\t</p>\r\n\t\t\t</div>\r\n\t\t\t<span style=\"-aw-bookmark-end:_Hlk213170018\">\r\n\t\t\t</span>\r\n\t\t\t<p>\r\n\t\t\t\t<span style=\"-aw-import:ignore\">&#xa0;</span>\r\n\t\t\t</p>\r\n\t\t</div>\r\n\t"
    },
    "dokutskottsforslag": {
      "utskottsforslag": {
        "punkt": "1",
        "rubrik": "Regeringens skrivelse",
        "forslag": "<BR/>Riksdagen lägger skrivelse 2025/26:9 till handlingarna.<BR/><BR/>",
        "beslutstyp": "acklamation",
        "motforslag_nummer": "0",
        "motforslag_partier": "",
        "votering_id": "",
        "votering_sammanfattning_html": "",
        "votering_url_xml": "",
        "rm": "2025/26",
        "bet": "SfU8",
        "vinnare": "utskottet",
        "voteringskrav": "",
        "beslutsregelkvot": "",
        "beslutsregelparagraf": "",
        "punkttyp": ""
      }
    },
    "dokaktivitet": {
      "aktivitet": [
        {
          "kod": "UBE",
          "namn": "Beredning",
          "datum": "2025-12-04 00:00:00",
          "status": "inträffat",
          "ordning": "0",
          "process": ""
        },
        {
          "kod": "UBE",
          "namn": "Beredning",
          "datum": "2025-12-11 00:00:00",
          "status": "inträffat",
          "ordning": "0",
          "process": ""
        },
        {
          "kod": "JUS",
          "namn": "Justering",
          "datum": "2026-01-13 00:00:00",
          "status": "inträffat",
          "ordning": "0",
          "process": ""
        },
        {
          "kod": "TRY",
          "namn": "Trycklov",
          "datum": "2026-01-14 00:00:00",
          "status": "inträffat",
          "ordning": "0",
          "process": ""
        },
        {
          "kod": "B",
          "namn": "Bordläggning",
          "datum": "2026-01-20 00:00:00",
          "status": "inträffat",
          "ordning": "0",
          "process": ""
        },
        {
          "kod": "BEH",
          "namn": "Behandling",
          "datum": "2026-01-21 00:00:00",
          "status": "inträffat",
          "ordning": "0",
          "process": ""
        },
        {
          "kod": "BES",
          "namn": "Beslut",
          "datum": "2026-01-28 00:00:00",
          "status": "inträffat",
          "ordning": "0",
          "process": ""
        }
      ]
    },
    "dokuppgift": {
      "uppgift": [
        {
          "kod": "arendestatuskammaren",
          "namn": "Beslutat",
          "text": "",
          "dok_id": "HD01SfU8",
          "systemdatum": "2026-01-28 16:42:30"
        },
        {
          "kod": "beslutdatumtid",
          "namn": "Datum och tid för beslutet",
          "text": "2026-01-28 00:00:00",
          "dok_id": "HD01SfU8",
          "systemdatum": "2026-01-28 16:34:02"
        },
        {
          "kod": "beslutssammanfattningusk",
          "namn": "Utskottets förslag till beslut",
          "text": "Skrivelsen läggs till handlingarna.",
          "dok_id": "HD01SfU8",
          "systemdatum": "2026-01-21 15:39:31"
        },
        {
          "kod": "debattdatumtid",
          "namn": "Datum och tid för debatten",
          "text": "2026-01-21 00:00:00",
          "dok_id": "HD01SfU8",
          "systemdatum": "2026-01-28 16:34:02"
        },
        {
          "kod": "notis",
          "namn": "Beslut i korthet",
          "text": "<p>Riksdagen har behandlat en skrivelse från regeringen som handlar om Riksrevisionens rapport om Migrationsverkets hantering av medborgarskapsärenden.</p>\n<p>Riksrevisionens övergripande bedömning är att Migrationsverkets hantering av medborgarskapsärenden inte är effektiv och har ett flertal brister. Bland annat när det kommer till att säkerställa korrekta beslut, samt att handläggningstiderna är oskäligt långa i många medborgarskapsärenden. Riksrevisionen lämnar även rekommendationer till Migrationsverket och regeringen om åtgärder för en effektivare hantering av medborgarskapsärenden och för att säkerställa korrekta beslut i dessa.  </p>\n<p>I sin skrivelse instämmer regeringen delvis i Riksrevisionens rekommendationer och pekar samtidigt på åtgärder som har vidtagits, bland annat ny lagstiftning, förstärkt styrning och effektivisering.</p>\n<p>Riksdagen vill betona vikten av att besluten i medborgarskapsärendena är korrekta och fattas inom rimlig tid. Riksdagen ser därför positivt på regeringens åtgärder för att förbättra hanteringen av ärendena. Med detta lade riksdagen regeringens skrivelse till handlingarna, det vill säga avslutade ärendet.</p>",
          "dok_id": "HD01SfU8",
          "systemdatum": "2026-01-28 16:34:02"
        },
        {
          "kod": "notisrubrik",
          "namn": "Beslut",
          "text": "Riksrevisionens rapport om Migrationsverkets hantering av medborgarskapsärenden har behandlats (SfU8)",
          "dok_id": "HD01SfU8",
          "systemdatum": "2026-01-28 16:34:02"
        },
        {
          "kod": "rdbeslut",
          "namn": "Riksdagens beslut",
          "text": "Kammaren biföll utskottets förslag.",
          "dok_id": "HD01SfU8",
          "systemdatum": "2026-01-28 16:42:30"
        },
        {
          "kod": "statustext",
          "namn": "statustext",
          "text": "Ärendet är avslutat",
          "dok_id": "HD01SfU8",
          "systemdatum": "2026-01-29 00:32:53"
        },
        {
          "kod": "utsknotis",
          "namn": "Utskottets förslag till beslut",
          "text": "<p>Socialförsäkringsutskottet har behandlat en skrivelse från regeringen som handlar om Riksrevisionens rapport om Migrationsverkets hantering av medborgarskapsärenden.</p>\n<p>Riksrevisionens övergripande bedömning är att Migrationsverkets hantering av medborgarskapsärenden inte är effektiv och har ett flertal brister. Bland annat när det kommer till att säkerställa korrekta beslut, samt att handläggningstiderna är oskäligt långa i många medborgarskapsärenden. Riksrevisionen lämnar även rekommendationer till Migrationsverket och regeringen om åtgärder för en effektivare hantering av medborgarskapsärenden och för att säkerställa korrekta beslut i dessa.  </p>\n<p>I sin skrivelse instämmer regeringen delvis i Riksrevisionens rekommendationer och pekar samtidigt på åtgärder som har vidtagits, bland annat ny lagstiftning, förstärkt styrning och effektivisering.</p>\n<p>Utskottet vill betona vikten av att besluten i medborgarskapsärendena är korrekta och fattas inom rimlig tid. Utskottet ser därför positivt på regeringens åtgärder för att förbättra hanteringen av ärendena. Med detta föreslår utskottet att riksdagen lägger regeringens skrivelse till handlingarna, det vill säga avslutar ärendet.</p>",
          "dok_id": "HD01SfU8",
          "systemdatum": "2026-01-28 16:34:02"
        },
        {
          "kod": "utsknotisrubrik",
          "namn": "Utskottets förslag",
          "text": "Riksrevisionens rapport om Migrationsverkets hantering av medborgarskapsärenden har behandlats (SfU8)",
          "dok_id": "HD01SfU8",
          "systemdatum": "2026-01-28 16:34:02"
        }
      ]
    },
    "dokbilaga": {
      "bilaga": [
        {
          "dok_id": "HD01SfU8",
          "subtitel": "",
          "filnamn": "2025_26_SfU8_20260114095809_Publicering.pdf",
          "filstorlek": "122871",
          "filtyp": "pdf",
          "titel": "Riksrevisionens rapport om Migrationsverkets hantering av medborgarskapsärenden",
          "fil_url": "https://data.riksdagen.se/fil/D9A2C9E7-0C0A-4376-877D-BC065E0D6A90"
        }
      ]
    },
    "dokreferens": {
      "referens": [
        {
          "referenstyp": "behandlar",
          "uppgift": "Skrivelse 2025/26:9 Riksrevisionens rapport om Migrationsverkets hantering av medborgarskapsärenden",
          "ref_dok_id": "HD039",
          "ref_dok_typ": "prop",
          "ref_dok_rm": "2025/26",
          "ref_dok_bet": "9",
          "ref_dok_titel": "Riksrevisionens rapport om Migrationsverkets hantering av medborgarskapsärenden",
          "ref_dok_subtitel": "",
          "ref_dok_subtyp": "skr",
          "ref_dok_dokumentnamn": "Regeringens skrivelse"
        },
        {
          "referenstyp": "beslut_id",
          "uppgift": "Beslut 2025/26:SfU8",
          "ref_dok_id": "HDC320260128SfU8",
          "ref_dok_typ": "kammakt",
          "ref_dok_rm": "2025/26",
          "ref_dok_bet": "SfU8",
          "ref_dok_titel": "Beslut: Riksrevisionens rapport om Migrationsverkets hantering av medborgarskapsärenden",
          "ref_dok_subtitel": "",
          "ref_dok_subtyp": "vo",
          "ref_dok_dokumentnamn": "Votering"
        },
        {
          "referenstyp": "föredragningslista",
          "uppgift": "föredragningslista 2025/26:61 Onsdag den 21 januari 2026",
          "ref_dok_id": "HD0I61",
          "ref_dok_typ": "f-lista",
          "ref_dok_rm": "2025/26",
          "ref_dok_bet": "61",
          "ref_dok_titel": "Onsdag den 21 januari 2026",
          "ref_dok_subtitel": "",
          "ref_dok_subtyp": "",
          "ref_dok_dokumentnamn": "Kammarens föredragningslista"
        },
        {
          "referenstyp": "protokollbeslut",
          "uppgift": "2026-01-28",
          "ref_dok_id": "HD0965",
          "ref_dok_typ": "prot",
          "ref_dok_rm": "2025/26",
          "ref_dok_bet": "65",
          "ref_dok_titel": "Protokoll 2025/26:65 Onsdagen den 28 januari",
          "ref_dok_subtitel": "Riksrevisionens rapport om Migrationsverkets hantering av medborgarskapsärenden",
          "ref_dok_subtyp": "",
          "ref_dok_dokumentnamn": "Protokoll"
        },
        {
          "referenstyp": "protokolldebatt",
          "uppgift": "2026-01-21",
          "ref_dok_id": "HD0961",
          "ref_dok_typ": "prot",
          "ref_dok_rm": "2025/26",
          "ref_dok_bet": "61",
          "ref_dok_titel": "Protokoll 2025/26:61 Onsdagen den 21 januari",
          "ref_dok_subtitel": "Riksrevisionens rapport om Migrationsverkets hantering av medborgarskapsärenden",
          "ref_dok_subtyp": "",
          "ref_dok_dokumentnamn": "Protokoll"
        },
        {
          "referenstyp": "rskr",
          "uppgift": "",
          "ref_dok_id": "HD0K143",
          "ref_dok_typ": "rskr",
          "ref_dok_rm": "2025/26",
          "ref_dok_bet": "143",
          "ref_dok_titel": "Riksdagsskrivelse 2025/26:143",
          "ref_dok_subtitel": "",
          "ref_dok_subtyp": "rskr",
          "ref_dok_dokumentnamn": "Riksdagsskrivelse"
        },
        {
          "referenstyp": "talarlista",
          "uppgift": "talarlista 2025/26:20260121 Onsdag den 21 januari 2026",
          "ref_dok_id": "HD0J20260121",
          "ref_dok_typ": "t-lista",
          "ref_dok_rm": "2025/26",
          "ref_dok_bet": "20260121",
          "ref_dok_titel": "Onsdag den 21 januari 2026",
          "ref_dok_subtitel": "",
          "ref_dok_subtyp": "",
          "ref_dok_dokumentnamn": "Talarlista"
        }
      ]
    }
  }
}